almvotes/__init__.py
almvotes/admin.py
almvotes/exceptions.py
almvotes/functions.py
almvotes/models.py
almvotes/tests.py
almvotes/views.py
almvotos/__init__.py
almvotos/settings.py
almvotos/urls.py
almvotos/wsgi.py
repoPruebaAlmVotes-1.0.dist-info/DESCRIPTION.rst
repoPruebaAlmVotes-1.0.dist-info/METADATA
repoPruebaAlmVotes-1.0.dist-info/RECORD
repoPruebaAlmVotes-1.0.dist-info/WHEEL
repoPruebaAlmVotes-1.0.dist-info/metadata.json
repoPruebaAlmVotes-1.0.dist-info/top_level.txt
